r00dialoger/__init__.py
r00dialoger/core.py
r00dialoger/helpers/__init__.py
r00dialoger/helpers/input.py
r00dialoger/helpers/options.py
r00dialoger/images/alert.ico
r00dialoger/images/alert.png
r00dialoger/images/alert_inverted.png
r00dialoger/images/error.ico
r00dialoger/images/error.png
r00dialoger/images/error_inverted.png
r00dialoger/images/info.ico
r00dialoger/images/info.png
r00dialoger/images/info_inverted.png
r00dialoger/images/question.ico
r00dialoger/images/question.png
r00dialoger/images/question_inverted.png
r00dialoger/images/success.ico
r00dialoger/images/success.png
r00dialoger/images/success_inverted.png
r00dialoger-0.1.5.dist-info/METADATA
r00dialoger-0.1.5.dist-info/WHEEL
r00dialoger-0.1.5.dist-info/RECORD
